LICENSE
MANIFEST.in
README.md
VERSION
requirements.txt
setup.cfg
setup.py
etc/custom.json
etc/default.json
etc/generate_people.json
etc/pass_postcode.json
etc/pass_urls.json
etc/random.json
src/anon_ai_toolbelt/__init__.py
src/anon_ai_toolbelt/aes.py
src/anon_ai_toolbelt/alias.py
src/anon_ai_toolbelt/auth.py
src/anon_ai_toolbelt/client.py
src/anon_ai_toolbelt/command.py
src/anon_ai_toolbelt/config.py
src/anon_ai_toolbelt/util.py
src/anon_ai_toolbelt.egg-info/PKG-INFO
src/anon_ai_toolbelt.egg-info/SOURCES.txt
src/anon_ai_toolbelt.egg-info/dependency_links.txt
src/anon_ai_toolbelt.egg-info/entry_points.txt
src/anon_ai_toolbelt.egg-info/not-zip-safe
src/anon_ai_toolbelt.egg-info/requires.txt
src/anon_ai_toolbelt.egg-info/top_level.txt