Metadata-Version: 1.2
Name: anon-ai-toolbelt
Version: 0.2.7
Summary: A command-line tool for using the Anon AI web service.
Home-page: https://github.com/anon-ai/toolbelt
Author: Anon AI
Author-email: info@anon.ai
License: MIT
Platform: UNKNOWN
Classifier: Development Status :: 4 - Beta
Classifier: Intended Audience :: Developers
Classifier: License :: OSI Approved :: MIT License
Classifier: Programming Language :: Python :: 3
Requires-Python: >=3
